mlperf_compliance/__init__.py
mlperf_compliance/_gnmt_tags.py
mlperf_compliance/_maskrcnn_tags.py
mlperf_compliance/_ncf_tags.py
mlperf_compliance/_resnet_tags.py
mlperf_compliance/_ssd_tags.py
mlperf_compliance/_transformer_tags.py
mlperf_compliance/mlperf_log.py
mlperf_compliance/resnet_log_helper.py
mlperf_compliance/tags.py
mlperf_compliance/test_tag_set.py
mlperf_compliance/tf_mlperf_log.py
mlperf_compliance-0.0.10.dist-info/LICENSE.md
mlperf_compliance-0.0.10.dist-info/METADATA
mlperf_compliance-0.0.10.dist-info/WHEEL
mlperf_compliance-0.0.10.dist-info/top_level.txt
mlperf_compliance-0.0.10.dist-info/RECORD
