Metadata-Version: 2.1
Name: mlperf_compliance
Version: 0.0.10
Summary: Tools for logging MLPerf compliance tags.
Home-page: https://github.com/mlperf/training/tree/master/compliance
Author: Taylor Robie
Author-email: taylorrobie@google.com
License: Apache 2.0
Platform: UNKNOWN
Classifier: Programming Language :: Python :: 2
Classifier: Programming Language :: Python :: 3
Classifier: License :: OSI Approved :: Apache Software License
Classifier: Operating System :: OS Independent
